[{"title":"Work on Frontend","date":"2021/5/21","status":"done","id":"7fb45c449d49"},{"title":"Handle CI & CD","date":"2021/5/21","status":"todo","id":"bb24"},{"title":"Add New Backend","date":"2021/5/22","status":"doing","id":"e0923c40-bb2b-11eb-8ae2-210f80351355"},{"title":"Another New Todo Created","date":"2021-05-27T19:42:00.606Z","status":"todo","id":"02491290-bbff-11eb-9323-4d2e37a71448"},{"title":"Added this todo","date":"2021-05-25T19:42:00.606Z","status":"doing","id":"f65476f0-bbfe-11eb-9323-4d2e37a71448"},{"title":"Add New Todo","date":"2021/5/26","status":"done","id":"d26a45e0-bb2b-11eb-b2c4-3f9a01b8f7ef"},{"title":"New Todo Item","date":"2021-05-28T19:42:00.606Z","status":"todo","id":"20c39590-bc01-11eb-9323-4d2e37a71448"},{"title":"do this item","date":"2021-05-25T19:42:00.606Z","status":"todo","id":"2b40fa80-bc01-11eb-9323-4d2e37a71448"},{"title":"Update list","date":"2021-05-25T19:42:00.606Z","status":"todo","id":"32bfc570-bc01-11eb-9323-4d2e37a71448"},{"title":"make it by weekend","date":"2021-05-25T19:42:00.606Z","status":"doing","id":"36f44760-bc01-11eb-9323-4d2e37a71448"}]